<?xml version="1.0"?>
<!DOCTYPE hibernate-mapping PUBLIC "-//Hibernate/Hibernate Mapping DTD 3.0//EN"
"http://hibernate.sourceforge.net/hibernate-mapping-3.0.dtd">
<!-- Generated 19/10/2010 02:40:32 by Hibernate Tools 3.2.1.GA -->
<hibernate-mapping>
    <class name="pojos.Pedido" table="pedido" schema="public">
        <id name="idpedido" type="long">
            <column name="idpedido" />
            <generator class="assigned" />
        </id>
        <many-to-one name="planprocesoscalidad" class="pojos.Planprocesoscalidad" fetch="select">
            <column name="planprocesoscalidad" />
        </many-to-one>
        <many-to-one name="presupuesto" class="pojos.Presupuesto" fetch="select">
            <column name="presupuesto" />
        </many-to-one>
        <many-to-one name="estadopedido" class="pojos.Estadopedido" fetch="select">
            <column name="estado" not-null="true" />
        </many-to-one>
        <many-to-one name="plano" class="pojos.Plano" fetch="select">
            <column name="plano" />
        </many-to-one>
        <many-to-one name="planprocedimientos" class="pojos.Planprocedimientos" fetch="select">
            <column name="planprocedimientos" />
        </many-to-one>
        <many-to-one name="prioridad" class="pojos.Prioridad" fetch="select">
            <column name="prioridad" not-null="true" />
        </many-to-one>
        <many-to-one name="factura" class="pojos.Factura" fetch="select">
            <column name="factura" />
        </many-to-one>
        <many-to-one name="planrequerimientosmateriaprima" class="pojos.Planrequerimientosmateriaprima" fetch="select">
            <column name="planrequerimientosmateriaprima" />
        </many-to-one>
        <many-to-one name="cliente" class="pojos.Cliente" fetch="select">
            <column name="cliente" />
        </many-to-one>
        <property name="nropedido" type="long">
            <column name="nropedido" not-null="true" unique="true" />
        </property>
        <property name="fechaconfirmacionpedido" type="date">
            <column name="fechaconfirmacionpedido" length="13" />
        </property>
        <property name="fechaentregaestipulada" type="date">
            <column name="fechaentregaestipulada" length="13" />
        </property>
        <property name="fechapedidocotizacion" type="date">
            <column name="fechapedidocotizacion" length="13" />
        </property>
        <property name="fechacancelacion" type="date">
            <column name="fechacancelacion" length="13" />
        </property>
        <property name="fechaentregareal" type="date">
            <column name="fechaentregareal" length="13" />
        </property>
        <property name="fecharequeridacotizacion" type="date">
            <column name="fecharequeridacotizacion" length="13" />
        </property>
        <property name="motivocancelacion" type="string">
            <column name="motivocancelacion" length="50" />
        </property>
        <property name="espedidoweb" type="java.lang.Boolean">
            <column name="espedidoweb" />
        </property>
        <property name="nropedidocotizacioncliente" type="java.lang.Integer">
            <column name="nropedidocotizacioncliente" />
        </property>
        <property name="fecharegpedcotiz" type="date">
            <column name="fecharegpedcotiz" length="13" />
        </property>
        <set name="productoreals" inverse="true">
            <key>
                <column name="idpedido" />
            </key>
            <one-to-many class="pojos.Productoreal" />
        </set>
        <set name="planificacionproduccions" inverse="true">
            <key>
                <column name="pedido" />
            </key>
            <one-to-many class="pojos.Planificacionproduccion" />
        </set>
        <set name="remitos" inverse="true">
            <key>
                <column name="pedido" />
            </key>
            <one-to-many class="pojos.Remito" />
        </set>
        <set name="detallefacturas" inverse="true">
            <key>
                <column name="idpedido" />
            </key>
            <one-to-many class="pojos.Detallefactura" />
        </set>
        <set name="planos" inverse="true">
            <key>
                <column name="pedido" />
            </key>
            <one-to-many class="pojos.Plano" />
        </set>
        <set name="trabajotercerizados" inverse="true">
            <key>
                <column name="pedido" />
            </key>
            <one-to-many class="pojos.Trabajotercerizado" />
        </set>
        <set name="detallepedidos" inverse="true">
            <key>
                <column name="idpedido" not-null="true" />
            </key>
            <one-to-many class="pojos.Detallepedido" />
        </set>
        <set name="planificacioncalidads" inverse="true">
            <key>
                <column name="pedido" />
            </key>
            <one-to-many class="pojos.Planificacioncalidad" />
        </set>
    </class>
</hibernate-mapping>
